[
    {
        "count": "1",
        "name":"Apple BD",
        "display": "true",
        "description": "We are here to help these people who want to buy apple mobiles. This is virtual service people can easily order products and cancel their order.This has an admin panel normal users can see their orders. they can give review. Admin users can do all normal users can do and also manage all orders , Add new service, Make someone admin",
        "site":"https://apple-bd.web.app/",
        "clientCode":"https://github.com/raihanuddin2002/apple-bd",
        "serverCode":"https://github.com/raihanuddin2002/apple-bd-server",
        "code":"",
        "type":"MERN",
        "picture":"https://i.ibb.co/v3sfBGq/screenshot-apple-bd-web-app-2021-11-30-07-01-50.png",
        "screenshorts":[
            "https://i.ibb.co/HYdfsBR/screenshot-apple-bd-web-app-2021-11-30-07-01-05.png",
            "https://i.ibb.co/YTqjFdR/screenshot-apple-bd-web-app-2021-12-01-18-39-40.png",
            "https://i.ibb.co/4pyB40N/01-12-2021-18-13-08-REC.png",
            "https://i.ibb.co/pyLRZvv/01-12-2021-18-16-26-REC.png"
        ],
        "category":"Apple Shop",
        "technologies": "html 5,css 3,react,bootstrap 5,express,mongoDB,firebase authentication,react router,Heroku"
    },
    {
        "count": "2",
        "name":"Traveler BD",
        "display": "true",
        "description": "We are here to help these people who want to buy apple mobiles. This is virtual service people can easily order products and cancel their order.This has an admin panel normal users can see their orders. they can give review. Admin users can do all normal users can do and also manage all orders , Add new service, Make someone admin",
        "site":"https://travellerbd-dd1c0.web.app/",
        "clientCode":"https://github.com/raihanuddin2002/traveler-bd-client-side",
        "serverCode":"https://github.com/raihanuddin2002/traveler-bd-server",
        "code":"",
        "type":"MERN",
        "picture":"https://i.ibb.co/DM2tXTW/01-12-2021-13-06-17-REC.png",
        "screenshorts":[
            "https://i.ibb.co/r6ktZtk/screenshot-travellerbd-dd1c0-web-app-2021-12-01-12-50-14.png",
            "https://i.ibb.co/51vPwfg/screenshot-travellerbd-dd1c0-web-app-2021-12-01-19-11-04.png",
            "https://i.ibb.co/d0M22MN/01-12-2021-19-00-29-REC.png"
        ],
        "category":"Travel Agency",
        "technologies": "html 5,css 3,react,bootstrap 5,express,mongoDB,firebase authentication,react router,Heroku"
    },
    {
        "count": "3",
        "name":"R HOSPITAL",
        "display": "true",
        "description": "We are here to help these people who want to buy apple mobiles. This is virtual service people can easily order products and cancel their order.This has an admin panel normal users can see their orders. they can give review. Admin users can do all normal users can do and also manage all orders , Add new service, Make someone admin",
        "site":"https://r-hospital-2002.web.app/",
        "client-code":"https://github.com/raihanuddin2002/r-hospital",
        "code":"",
        "server-code":"https://github.com/raihanuddin2002/traveler-bd-server",
        "type":"REACT",
        "picture":"https://i.ibb.co/pPC56dG/01-12-2021-13-00-33-REC.png",
        "screenshorts":[
            "https://i.ibb.co/3R19jN1/screenshot-r-hospital-2002-web-app-2021-12-01-19-06-23.png",
            "https://i.ibb.co/WWSYgpp/01-12-2021-19-08-17-REC.png",
            "https://i.ibb.co/NpkYb48/screenshot-r-hospital-2002-web-app-2021-12-01-19-09-33.png"
        ],
        "category":"online hospital",
        "technologies": "html 5,css 3,react,bootstrap 5,firebase,react router"
        

    },
    {
        "count": "4",
        "name":"SS CHAT",
        "display": "true",
        "description": "We are here to help these people who want to buy apple mobiles. This is virtual service people can easily order products and cancel their order.This has an admin panel normal users can see their orders. they can give review. Admin users can do all normal users can do and also manage all orders , Add new service, Make someone admin",
        "site":"https://raihanuddin2002.xyz/",
        "client-code":"",
        "server-code":"",
        "code":"https://github.com/raihanuddin2002/SS-Chat",
        "type":"PHP",
        "picture":"https://i.ibb.co/2KZHssV/01-12-2021-13-02-54-REC.png",
        "screenshorts":[
            "https://i.ibb.co/GQzHFxR/01-12-2021-19-15-15-REC.png",
            "https://i.ibb.co/z85pZt0/screenshot-raihanuddin2002-xyz-2021-12-01-19-15-35.png",
            "https://i.ibb.co/25hRfwq/screenshot-raihanuddin2002-xyz-2021-12-01-19-18-17.png",
            "https://i.ibb.co/GQ7TNkQ/01-12-2021-19-14-37-REC.png"
        ],
        "category":"Real time chat application",
        "technologies": "html 5,css 3,bootstrap 5,jquery,php,mysql,ajax,cpanel"
    }
    
]